Defines.vh
//  LUMOS - Light Utilization with Multicycle Operational Stages
//  A RISC-V RV32I Processor Core

//  Description: LUMOS Core Definitions
//  Copyright 2024 Iran University of Science and Technology. <iustCompOrg@gmail.com>

//  Permission to use, copy, modify, and/or distribute this software for any
//  purpose with or without fee is hereby granted, provided that the above
//  copyright notice and this permission notice appear in all copies.

`ifndef OPCODES
    `define LOAD        7'b00_000_11
    `define LOAD_FP     7'b00_001_11
    `define custom_0    7'b00_010_11
    `define MISC_MEM    7'b00_011_11
    `define OP_IMM      7'b00_100_11
    `define AUIPC       7'b00_101_11
    `define OP_IMM_32   7'b00_110_11

    `define STORE       7'b01_000_11
    `define STORE_FP    7'b01_001_11
    `define custom_1    7'b01_010_11
    `define AMO         7'b01_011_11
    `define OP          7'b01_100_11
    `define LUI         7'b01_101_11
    `define OP_32       7'b01_110_11

    `define MADD        7'b10_000_11
    `define MSUB        7'b10_001_11
    `define NMSUB       7'b10_010_11
    `define NMADD       7'b10_011_11
    `define OP_FP       7'b10_100_11
    `define custom_2    7'b10_110_11

    `define BRANCH      7'b11_000_11
    `define JALR        7'b11_001_11
    `define JAL         7'b11_011_11
    `define SYSTEM      7'b11_100_11
    `define custom_3    7'b11_110_11
`endif /*OPCODES*/

`ifndef INSTRUCTION_TYPES
    `define R_TYPE      0
    `define I_TYPE      1
    `define S_TYPE      2
    `define B_TYPE      3
    `define U_TYPE      4
    `define J_TYPE      5
`endif /*INSTRUCTION_TYPES*/

`ifndef I_INSTRUCTIONS
    `define ADDI        3'b000
    `define SLTI        3'b010
    `define SLTIU       3'b011
    `define XORI        3'b100
    `define ORI         3'b110
    `define ANDI        3'b111
    `define SLLI        3'b001      // Shift Left Immediate -> Logical
    `define SRI         3'b101      // Shift Right Immediate -> Logical & Arithmetic
`endif /*I_INSTRUCTIONS*/

`ifndef R_INSTRUCTIONS
    `define ADDSUB      3'b000
    `define SLL         3'b001      // Shift Left -> Logical   
    `define SLT         3'b010
    `define SLTU        3'b011    
    `define XOR         3'b100    
    `define SR          3'b101      // Shift Right -> Logical & Arithmetic   
    `define OR          3'b110    
    `define AND         3'b111
`endif /*R_INSTRUCTIONS*/

`ifndef MUL_DIV_INSTRCUTIONS
    `define MUL         3'b000
    `define MULH        3'b001
    `define MULHSU      3'b010
    `define MULHU       3'b011 

    `define DIV         3'b100
    `define DIVU        3'b101
    `define REM         3'b110
    `define REMU        3'b111

    `define MULDIV      7'b0000001
`endif /*MUL_DIV_INSTRCUTIONS*/

`ifndef FIXED_POINT_INSTRUCTIONS
    `define FADD        7'b000_0000
    `define FSUB        7'b000_0100

    `define FMUL        7'b000_1000
    `define FDIV        7'b000_1100 

    `define FSQRT       7'b010_1100
`endif /*FIXED_POINT_INSTRUCTIONS*/

`ifndef BRANCH_INSTRUCTIONS
    `define BEQ         3'b000
    `define BNE         3'b001
    `define BLT         3'b100
    `define BGE         3'b101
    `define BLTU        3'b110
    `define BGEU        3'b111
`endif /*BRANCH_INSTRUCTIONS*/

`ifndef ALU_OPERATIONS
    `define ALU_ADD     4'b0000
    `define ALU_SUB     4'b0001
    `define ALU_AND     4'b0010
    `define ALU_OR      4'b0011
    `define ALU_XOR     4'b0100
    `define ALU_SLT     4'b0101 
    `define ALU_SLTU    4'b0110
    `define ALU_SLL     4'b0111 
    `define ALU_SRL     4'b1000
    `define ALU_SRA     4'b1001
`endif /*ALU_OPERATIONS*/

`ifndef ALU_AUXILIARY_DEFINES
    `define LOGICAL     7'b000_0000
    `define ARITHMETIC  7'b010_0000
    `define ADD         7'b000_0000     
    `define SUB         7'b010_0000
`endif /*ALU_AUXILIARY_DEFINES*/

`ifndef FPU_OPERATIONS
    `define FPU_ADD     2'b00
    `define FPU_SUB     2'b01
    `define FPU_MUL     2'b10
    `define FPU_SQRT    2'b11
`endif /*FPU_OPERATIONS*/

`ifndef ALU_SRC_SELECT
    `define PC          2'b00
    `define RS1         2'b01
    `define ALU_RESULT  2'b10
    `define ZERO        2'b11

    `define RS2         2'b00
    `define FOUR        2'b01
    `define IMMEDIATE   2'b10
`endif /*ALU_SRC_SELECT*/

`ifndef REGISTER_FILE_WRITE_SOURCE
    `define MEMORY      2'b00
    `define ALU         2'b01
    `define NEXT_PC     2'b10
    `define FPU         2'b11
`endif /*REGISTER_FILE_WRITE_SOURCE*/

`ifndef CONTROL_SIGNALS
    `define INSTRUCTION     1'b0
    `define DATA            1'b1

    `define READ            1'b0
    `define WRITE           1'b1

    `define DISABLE         1'b0
    `define ENABLE          1'b1
`endif /*CONTROL_SIGNALS*/

`ifndef CONTROLLER_STATES
    `define RESET               0
    `define FETCH_BEGIN         1
    `define FETCH_WAIT          2
    `define FETCH_DONE          3
    `define DECODE              4
    `define EXECUTE             5
    `define EXECUTE_BRANCH      6
    `define TAKE_BRANCH         7
    `define EXECUTE_JUMP        8
    `define MEMORY_WRITE        9
    `define MEMORY_READ_BEGIN   10
    `define MEMORY_READ_WAIT    11
    `define MEMORY_READ_DONE    12
    `define EXECUTE_FP          13
`endif /*CONTROLLER_STATES*/

Fixed_Point_Unit.v
`include "Defines.vh"

module Fixed_Point_Unit 
#(
    parameter WIDTH = 32,
    parameter FBITS = 10
)
(
    input wire clk,
    input wire reset,
    
    input wire [WIDTH - 1 : 0] operand_1,
    input wire [WIDTH - 1 : 0] operand_2,
    
    input wire [ 1 : 0] operation,

    output reg [WIDTH - 1 : 0] result,
    output reg ready
);

    always @(*)
    begin
        case (operation)
            `FPU_ADD    : begin result = operand_1 + operand_2; ready = 1; end
            `FPU_SUB    : begin result = operand_1 - operand_2; ready = 1; end
            `FPU_MUL    : begin result = product[WIDTH + FBITS - 1 : FBITS]; ready = product_ready; end
            `FPU_SQRT   : begin result = root; ready = root_ready; end
            default     : begin result = 'bz; ready = 0; end
        endcase
    end

    always @(posedge reset)
    begin
        if (reset)  ready = 0;
        else        ready = 'bz;
    end
    // ------------------- //
    // Square Root Circuit //
    // ------------------- //
    reg [WIDTH - 1 : 0] root;
    reg root_ready;

    reg [1 : 0] square_root_stage;
    reg [1 : 0] next_square_root_stage;

    always @(posedge clk) 
    begin
        if (operation == `FPU_SQRT) square_root_stage <= next_square_root_stage;
        else                        
        begin
            square_root_stage <= 2'b00;
            root_ready <= 0;
        end
    end 

    always @(*) 
    begin
        next_square_root_stage <= 'bz;
        case (square_root_stage)
            2'b00 : begin sqrt_start <= 0; next_square_root_stage <= 2'b01; end
            2'b01 : begin sqrt_start <= 1; next_square_root_stage <= 2'b10; end
            2'b10 : begin sqrt_start <= 0; next_square_root_stage <= 2'b10; end
        endcase    
    end
    reg sqrt_start;
    reg sqrt_busy;
    
    reg [WIDTH - 1 : 0] x, x_next;              
    reg [WIDTH - 1 : 0] q, q_next;              
    reg [WIDTH + 1 : 0] ac, ac_next;            
    reg [WIDTH + 1 : 0] test_res;               

    reg valid;

    localparam ITER = (WIDTH + FBITS) >> 1;     
    reg [4 : 0] i = 0;                              

    always @(*)
    begin
        test_res = ac - {q, 2'b01};

        if (test_res[WIDTH + 1] == 0) 
        begin
            {ac_next, x_next} = {test_res[WIDTH - 1 : 0], x, 2'b0};
            q_next = {q[WIDTH - 2 : 0], 1'b1};
        end 
        else 
        begin
            {ac_next, x_next} = {ac[WIDTH - 1 : 0], x, 2'b0};
            q_next = q << 1;
        end
    end
    
    always @(posedge clk) 
    begin
        if (sqrt_start)
        begin
            sqrt_busy <= 1;
            root_ready <= 0;
            i <= 0;
            q <= 0;
            {ac, x} <= {{WIDTH{1'b0}}, operand_1, 2'b0};
        end

        else if (sqrt_busy)
        begin
            if (i == ITER-1) 
            begin  // we're done
                sqrt_busy <= 0;
                root_ready <= 1;
                root <= q_next;
            end

            else 
            begin  // next iteration
                i <= i + 1;
                x <= x_next;
                ac <= ac_next;
                q <= q_next;
                root_ready <= 0;
            end
        end
    end

    // ------------------ //
    // Multiplier Circuit //
    // ------------------ //   
    reg [64 - 1 : 0] product;
    reg product_ready;

    reg     [15 : 0] multiplierCircuitInput1;
    reg     [15 : 0] multiplierCircuitInput2;
    wire    [31 : 0] multiplierCircuitResult;

    Multiplier multiplier_circuit
    (
        .operand_1(multiplierCircuitInput1),
        .operand_2(multiplierCircuitInput2),
        .product(multiplierCircuitResult)
    );

    reg     [31 : 0] partialProduct1;
    reg     [31 : 0] partialProduct2;
    reg     [31 : 0] partialProduct3;
    reg     [31 : 0] partialProduct4;

    reg [2 : 0] multiplication_stage;
    reg [2 : 0] next_multiplication_stage;

    always @(posedge clk) 
    begin
        if (operation == `FPU_MUL)  multiplication_stage <= next_multiplication_stage;
        else                        multiplication_stage <= 'b0;
    end

    always @(*) 
    begin
        next_multiplication_stage <= 'bz;
        case (multiplication_stage)
            3'b000 :
            begin
                product_ready <= 0;

                multiplierCircuitInput1 <= 'bz;
                multiplierCircuitInput2 <= 'bz;

                partialProduct1 <= 'bz;
                partialProduct2 <= 'bz;
                partialProduct3 <= 'bz;
                partialProduct4 <= 'bz;

                next_multiplication_stage <= 3'b001;
            end 
            3'b001 : 
            begin
                multiplierCircuitInput1 <= operand_1[15 : 0];
                multiplierCircuitInput2 <= operand_2[15 : 0];
                partialProduct1 <= multiplierCircuitResult;
                next_multiplication_stage <= 3'b010;
            end
            3'b010 : 
            begin
                multiplierCircuitInput1 <= operand_1[31 : 16];
                multiplierCircuitInput2 <= operand_2[15 : 0];
                partialProduct2 <= multiplierCircuitResult;
                next_multiplication_stage <= 3'b011;
            end
            3'b011 : 
            begin
                multiplierCircuitInput1 <= operand_1[15 : 0];
                multiplierCircuitInput2 <= operand_2[31 : 16];
                partialProduct3 <= multiplierCircuitResult;
                next_multiplication_stage <= 3'b100;
            end
            3'b100 : 
            begin
                multiplierCircuitInput1 <= operand_1[31 : 16];
                multiplierCircuitInput2 <= operand_2[31 : 16];
                partialProduct4 <= multiplierCircuitResult;
                next_multiplication_stage <= 3'b101;
            end
            3'b101 :
            begin
                product <= partialProduct1 + (partialProduct2 << 16) + (partialProduct3 << 16) + (partialProduct4 << 32);
                next_multiplication_stage <= 3'b000;
                product_ready <= 1;
            end

            default: next_multiplication_stage <= 3'b000;
        endcase    
    end
endmodule

module Multiplier
(
    input wire [15 : 0] operand_1,
    input wire [15 : 0] operand_2,

    output reg [31 : 0] product
);

    always @(*)
    begin
        product <= operand_1 * operand_2;
    end
endmodule

Fixed_Point_Unit_Testbench.v
`timescale 1 ns / 1 ns

`include "Fixed_Point_Unit.v"

module Fixed_Point_Unit_Testbench;

    //////////////////////
    // Clock Generation //
    //////////////////////
    parameter CLK_PERIOD = 4;
    reg clk = 1'b1;
    initial begin forever #(CLK_PERIOD/2) clk = ~clk; end
    reg reset = `ENABLE;    

    /////////////////
    // FPU Signals //
    /////////////////

    reg [31 : 0] operand_1;
    reg [31 : 0] operand_2;
    reg [ 1 : 0] operation;

    wire [31 : 0] fpu_result;
    wire fpu_ready;

    Fixed_Point_Unit 
    #(
        .WIDTH(32),
        .FBITS(10)
    )
    uut
    (
        .clk(clk),
        .reset(reset),

        .operand_1(operand_1),
        .operand_2(operand_2),
        
        .operation(operation),

        .result(fpu_result),
        .ready(fpu_ready)
    );
    
    initial 
    begin
        $dumpfile("Fixed_Point_Unit.vcd");    
        $dumpvars(0, Fixed_Point_Unit_Testbench);
        repeat (3) @(posedge clk);
        reset <= `DISABLE;

        repeat (2) @(posedge clk);
        operand_1 = 32'b0000_0011_1010_0000_00;
        operand_2 = 32'b0000_0100_0001_0000_00;
        operation = `FPU_ADD;

        repeat (1) @(posedge clk);
        operand_1 = 'bz;
        operand_2 = 'bz;
        operation = 'bz;

        repeat (1) @(posedge clk);
        operand_1 = 32'b0000_0011_1010_0000_00;
        operand_2 = 32'b0000_0001_1000_0000_00;
        operation = `FPU_SUB;

        repeat (1) @(posedge clk);
        operand_1 = 'bz;
        operand_2 = 'bz;
        operation = 'bz;

        repeat (1) @(posedge clk);
        operand_1 = 32'b0000_0011_1010_0000_00;
        operand_2 = 32'b0000_0001_1000_0000_00;
        operation = `FPU_MUL;

        repeat (1) @(posedge fpu_ready);
        repeat (1) @(posedge clk);
        operand_1 = 'bz;
        operand_2 = 'bz;
        operation = 'bz;

        repeat (1) @(posedge clk);
        operand_1 = 'b11100110000000000;
        operation = `FPU_SQRT;

        repeat (1) @(posedge fpu_ready);
        repeat (3) @(posedge clk);
        operand_1 = 'bz;
        operand_2 = 'bz;
        operation = 'bz;

        repeat (10) @(posedge clk);
        $dumpoff;
        $finish;
    end
endmodule

Fixed_Point_Unit.vcd
$date
	Tue Jul 02 23:31:19 2024
$end
$version
	Icarus Verilog
$end
$timescale
	1ns
$end
$scope module Fixed_Point_Unit_Testbench $end
$var wire 32 ! fpu_result [31:0] $end
$var wire 1 " fpu_ready $end
$var parameter 32 # CLK_PERIOD $end
$var reg 1 $ clk $end
$var reg 32 % operand_1 [31:0] $end
$var reg 32 & operand_2 [31:0] $end
$var reg 2 ' operation [1:0] $end
$var reg 1 ( reset $end
$scope module uut $end
$var wire 1 $ clk $end
$var wire 32 ) operand_1 [31:0] $end
$var wire 32 * operand_2 [31:0] $end
$var wire 2 + operation [1:0] $end
$var wire 1 ( reset $end
$var wire 32 , multiplierCircuitResult [31:0] $end
$var parameter 32 - FBITS $end
$var parameter 32 . ITER $end
$var parameter 32 / WIDTH $end
$var reg 34 0 ac [33:0] $end
$var reg 34 1 ac_next [33:0] $end
$var reg 5 2 i [4:0] $end
$var reg 3 3 multiplication_stage [2:0] $end
$var reg 16 4 multiplierCircuitInput1 [15:0] $end
$var reg 16 5 multiplierCircuitInput2 [15:0] $end
$var reg 3 6 next_multiplication_stage [2:0] $end
$var reg 2 7 next_square_root_stage [1:0] $end
$var reg 32 8 partialProduct1 [31:0] $end
$var reg 32 9 partialProduct2 [31:0] $end
$var reg 32 : partialProduct3 [31:0] $end
$var reg 32 ; partialProduct4 [31:0] $end
$var reg 64 < product [63:0] $end
$var reg 1 = product_ready $end
$var reg 32 > q [31:0] $end
$var reg 32 ? q_next [31:0] $end
$var reg 1 " ready $end
$var reg 32 @ result [31:0] $end
$var reg 32 A root [31:0] $end
$var reg 1 B root_ready $end
$var reg 1 C sqrt_busy $end
$var reg 1 D sqrt_start $end
$var reg 2 E square_root_stage [1:0] $end
$var reg 34 F test_res [33:0] $end
$var reg 32 G x [31:0] $end
$var reg 32 H x_next [31:0] $end
$scope module multiplier_circuit $end
$var wire 16 I operand_1 [15:0] $end
$var wire 16 J operand_2 [15:0] $end
$var reg 32 K product [31:0] $end
$upscope $end
$upscope $end
$upscope $end
$enddefinitions $end
$comment Show the parameter values. $end
$dumpall
b100000 /
b10101 .
b1010 -
b100 #
$end
#0
$dumpvars
bx K
bz J
bz I
bx H
bx G
bx F
b0 E
0D
xC
0B
bx A
bz @
bx ?
bx >
0=
bx <
bz ;
bz :
bz 9
bz 8
b1 7
b1 6
bz 5
bz 4
b0 3
b0 2
bx 1
bx 0
bx ,
bx +
bx *
bx )
1(
bx '
bx &
bx %
1$
0"
bz !
$end
#2
0$
#4
1$
#6
0$
#8
1$
#10
0$
#12
0(
1$
#14
0$
#16
1$
#18
0$
#20
b1 6
1"
b1111011000000 !
b1111011000000 @
b0 '
b0 +
b1000001000000 &
b1000001000000 *
b111010000000 %
b111010000000 )
1$
#22
0$
#24
b1 6
0"
bz !
bz @
bz '
bz +
bz &
bz *
bz %
bz )
1$
#26
0$
#28
b1 6
1"
b100010000000 !
b100010000000 @
b1 '
b1 +
b11000000000 &
b11000000000 *
b111010000000 %
b111010000000 )
1$
#30
0$
#32
b1 6
0"
bz !
bz @
bz '
bz +
bz &
bz *
bz %
bz )
1$
#34
0$
#36
b1 6
bx !
bx @
b10 '
b10 +
b11000000000 &
b11000000000 *
b111010000000 %
b111010000000 )
1$
#38
0$
#40
b10101110000000000000000 ,
b10101110000000000000000 K
b10101110000000000000000 8
b11000000000 5
b11000000000 J
b111010000000 4
b111010000000 I
b10 6
b1 3
1$
#42
0$
#44
b0 ,
b0 K
b0 9
b0 4
b0 I
b11 6
b10 3
1$
#46
0$
#48
b0 :
b0 5
b0 J
b111010000000 4
b111010000000 I
b100 6
b11 3
1$
#50
0$
#52
b0 ;
b0 4
b0 I
b101 6
b100 3
1$
#54
0$
#56
1"
b1010111000000 !
b1010111000000 @
1=
b10101110000000000000000 <
b0 6
b101 3
1$
#58
0$
#60
bx ,
bx K
bz ;
bz :
bz 9
bz 8
bz 5
bz J
bz 4
bz I
0=
b1 6
b0 3
0"
bz !
bz @
bz '
bz +
bz &
bz *
bz %
bz )
1$
#62
0$
#64
b1 6
bx !
bx @
b11 '
b11 +
b11100110000000000 %
b11100110000000000 )
1$
#66
0$
#68
1D
b10 7
b1 E
1$
#70
0$
#72
0D
b10 7
b0 ?
b0 1
b111001100000000000000 H
b1111111111111111111111111111111111 F
b10 E
b0 0
b1110011000000000000 G
b0 >
1C
1$
#74
0$
#76
b11100110000000000000000 H
b111001100000000000000 G
b1 2
1$
#78
0$
#80
b1110011000000000000000000 H
b11100110000000000000000 G
b10 2
1$
#82
0$
#84
b111001100000000000000000000 H
b1110011000000000000000000 G
b11 2
1$
#86
0$
#88
b11100110000000000000000000000 H
b111001100000000000000000000 G
b100 2
1$
#90
0$
#92
b1110011000000000000000000000000 H
b11100110000000000000000000000 G
b101 2
1$
#94
0$
#96
b1 1
b11001100000000000000000000000000 H
b1110011000000000000000000000000 G
b110 2
1$
#98
0$
#100
b1 ?
b11 1
b110000000000000000000000000000 H
b0 F
b1 0
b11001100000000000000000000000000 G
b111 2
1$
#102
0$
#104
b10 ?
b1100 1
b11000000000000000000000000000000 H
b1111111111111111111111111111111110 F
b1 >
b11 0
b110000000000000000000000000000 G
b1000 2
1$
#106
0$
#108
b101 ?
b1111 1
b0 H
b11 F
b10 >
b1100 0
b11000000000000000000000000000000 G
b1001 2
1$
#110
0$
#112
b1010 ?
b111100 1
b1111111111111111111111111111111010 F
b101 >
b1111 0
b0 G
b1010 2
1$
#114
0$
#116
b10101 ?
b1001100 1
b10011 F
b1010 >
b111100 0
b1011 2
1$
#118
0$
#120
b101010 ?
b100110000 1
b1111111111111111111111111111110111 F
b10101 >
b1001100 0
b1100 2
1$
#122
0$
#124
b1010101 ?
b1000011100 1
b10000111 F
b101010 >
b100110000 0
b1101 2
1$
#126
0$
#128
b10101011 ?
b1100011100 1
b11000111 F
b1010101 >
b1000011100 0
b1110 2
1$
#130
0$
#132
b101010111 ?
b110111100 1
b1101111 F
b10101011 >
b1100011100 0
b1111 2
1$
#134
0$
#136
b1010101110 ?
b11011110000 1
b1111111111111111111111110001011111 F
b101010111 >
b110111100 0
b10000 2
1$
#138
0$
#140
b10101011100 ?
b1101111000000 1
b1111111111111111111111110000110111 F
b1010101110 >
b11011110000 0
b10001 2
1$
#142
0$
#144
b101010111001 ?
b1100100111100 1
b11001001111 F
b10101011100 >
b1101111000000 0
b10010 2
1$
#146
0$
#148
b1010101110010 ?
b110010011110000 1
b1111111111111111111110111001010111 F
b101010111001 >
b1100100111100 0
b10011 2
1$
#150
0$
#152
b10101011100101 ?
b11110010011100 1
b111100100111 F
b1010101110010 >
b110010011110000 0
b10100 2
1$
#154
0$
#156
1"
b10101011100101 !
b10101011100101 @
b10101011100101 A
1B
0C
1$
#158
0$
#160
1$
#162
0$
#164
1$
#166
0$
#168
b1 7
b1 6
0B
b0 E
0"
bz !
bz @
bz '
bz +
bz %
bz )
1$
#170
0$
#172
1$
#174
0$
#176
1$
#178
0$
#180
1$
#182
0$
#184
1$
#186
0$
#188
1$
#190
0$
#192
1$
#194
0$
#196
1$
#198
0$
#200
1$
#202
0$
#204
1$
#206
0$
#208
$dumpoff
bx K
bx J
bx I
bx H
bx G
bx F
bx E
xD
xC
xB
bx A
bx @
bx ?
bx >
x=
bx <
bx ;
bx :
bx 9
bx 8
bx 7
bx 6
bx 5
bx 4
bx 3
bx 2
bx 1
bx 0
bx ,
bx +
bx *
bx )
x(
bx '
bx &
bx %
x$
x"
bx !
$end
1$